<?xml version="1.0" encoding="UTF-8" ?>
<feature
	id="org.eclipse.babel.nls_tools.tm_de"
	label="Babel Language Pack for tools.tm in German (24.71%)"
	image="eclipse_update_120.jpg"
	provider-name="%providerName"
	version="4.5.0.v20150804081228">
	<copyright>
		%copyright
	</copyright>
	<license url="%licenseURL">
		%license
	</license>
	<description>Babel Language Pack for tools.tm in German</description>
	<plugin fragment="true" id="org.eclipse.dstore.core.nl_de" unpack="false" version="4.5.0.v20150804081228" download-size="1377" install-size="1377" />
	<plugin fragment="true" id="org.eclipse.dstore.doc.isv.nl_de" unpack="false" version="4.5.0.v20150804081228" download-size="1409" install-size="1409" />
	<plugin fragment="true" id="org.eclipse.dstore.extra.nl_de" unpack="false" version="4.5.0.v20150804081228" download-size="1376" install-size="1376" />
	<plugin fragment="true" id="org.eclipse.rse.connectorservice.dstore.nl_de" unpack="false" version="4.5.0.v20150804081228" download-size="1387" install-size="1387" />
	<plugin fragment="true" id="org.eclipse.rse.connectorservice.local.nl_de" unpack="false" version="4.5.0.v20150804081228" download-size="1386" install-size="1386" />
	<plugin fragment="true" id="org.eclipse.rse.connectorservice.ssh.nl_de" unpack="false" version="4.5.0.v20150804081228" download-size="2766" install-size="2766" />
	<plugin fragment="true" id="org.eclipse.rse.connectorservice.telnet.nl_de" unpack="false" version="4.5.0.v20150804081228" download-size="1386" install-size="1386" />
	<plugin fragment="true" id="org.eclipse.rse.core-feature.nl_de" unpack="false" version="4.5.0.v20150804081228" download-size="1540" install-size="1540" />
	<plugin fragment="true" id="org.eclipse.rse.core.nl_de" unpack="false" version="4.5.0.v20150804081228" download-size="2406" install-size="2406" />
	<plugin fragment="true" id="org.eclipse.rse.doc.isv.nl_de" unpack="false" version="4.5.0.v20150804081228" download-size="1377" install-size="1377" />
	<plugin fragment="true" id="org.eclipse.rse.doc.user.nl_de" unpack="false" version="4.5.0.v20150804081228" download-size="1377" install-size="1377" />
	<plugin fragment="true" id="org.eclipse.rse.dstore-feature.nl_de" unpack="false" version="4.5.0.v20150804081228" download-size="1541" install-size="1541" />
	<plugin fragment="true" id="org.eclipse.rse.dstore.security.nl_de" unpack="false" version="4.5.0.v20150804081228" download-size="2617" install-size="2617" />
	<plugin fragment="true" id="org.eclipse.rse.efs.nl_de" unpack="false" version="4.5.0.v20150804081228" download-size="2263" install-size="2263" />
	<plugin fragment="true" id="org.eclipse.rse.efs.ui.nl_de" unpack="false" version="4.5.0.v20150804081228" download-size="2387" install-size="2387" />
	<plugin fragment="true" id="org.eclipse.rse.examples-feature.nl_de" unpack="false" version="4.5.0.v20150804081228" download-size="1542" install-size="1542" />
	<plugin fragment="true" id="org.eclipse.rse.examples.daytime.nl_de" unpack="false" version="4.5.0.v20150804081228" download-size="1382" install-size="1382" />
	<plugin fragment="true" id="org.eclipse.rse.examples.dstore.nl_de" unpack="false" version="4.5.0.v20150804081228" download-size="1379" install-size="1379" />
	<plugin fragment="true" id="org.eclipse.rse.examples.tutorial.nl_de" unpack="false" version="4.5.0.v20150804081228" download-size="1914" install-size="1914" />
	<plugin fragment="true" id="org.eclipse.rse.files.ui.nl_de" unpack="false" version="4.5.0.v20150804081228" download-size="3663" install-size="3663" />
	<plugin fragment="true" id="org.eclipse.rse.ftp-feature.nl_de" unpack="false" version="4.5.0.v20150804081228" download-size="1539" install-size="1539" />
	<plugin fragment="true" id="org.eclipse.rse.importexport.nl_de" unpack="false" version="4.5.0.v20150804081228" download-size="4578" install-size="4578" />
	<plugin fragment="true" id="org.eclipse.rse.local-feature.nl_de" unpack="false" version="4.5.0.v20150804081228" download-size="1541" install-size="1541" />
	<plugin fragment="true" id="org.eclipse.rse.nl_de" unpack="false" version="4.5.0.v20150804081228" download-size="1368" install-size="1368" />
	<plugin fragment="true" id="org.eclipse.rse.processes.ui.nl_de" unpack="false" version="4.5.0.v20150804081228" download-size="3243" install-size="3243" />
	<plugin fragment="true" id="org.eclipse.rse.scp-feature.nl_de" unpack="false" version="4.5.0.v20150804081228" download-size="1539" install-size="1539" />
	<plugin fragment="true" id="org.eclipse.rse.sdk.nl_de" unpack="false" version="4.5.0.v20150804081228" download-size="1374" install-size="1374" />
	<plugin fragment="true" id="org.eclipse.rse.services.dstore.nl_de" unpack="false" version="4.5.0.v20150804081228" download-size="3001" install-size="3001" />
	<plugin fragment="true" id="org.eclipse.rse.services.files.ftp.nl_de" unpack="false" version="4.5.0.v20150804081228" download-size="2623" install-size="2623" />
	<plugin fragment="true" id="org.eclipse.rse.services.local.nl_de" unpack="false" version="4.5.0.v20150804081228" download-size="2470" install-size="2470" />
	<plugin fragment="true" id="org.eclipse.rse.services.nl_de" unpack="false" version="4.5.0.v20150804081228" download-size="3340" install-size="3340" />
	<plugin fragment="true" id="org.eclipse.rse.services.ssh.nl_de" unpack="false" version="4.5.0.v20150804081228" download-size="2435" install-size="2435" />
	<plugin fragment="true" id="org.eclipse.rse.services.telnet.nl_de" unpack="false" version="4.5.0.v20150804081228" download-size="2455" install-size="2455" />
	<plugin fragment="true" id="org.eclipse.rse.shells.ui.nl_de" unpack="false" version="4.5.0.v20150804081228" download-size="2603" install-size="2603" />
	<plugin fragment="true" id="org.eclipse.rse.ssh-feature.nl_de" unpack="false" version="4.5.0.v20150804081228" download-size="1540" install-size="1540" />
	<plugin fragment="true" id="org.eclipse.rse.subsystems.files.core.nl_de" unpack="false" version="4.5.0.v20150804081228" download-size="2925" install-size="2925" />
	<plugin fragment="true" id="org.eclipse.rse.subsystems.files.dstore.nl_de" unpack="false" version="4.5.0.v20150804081228" download-size="1398" install-size="1398" />
	<plugin fragment="true" id="org.eclipse.rse.subsystems.files.ftp.nl_de" unpack="false" version="4.5.0.v20150804081228" download-size="1422" install-size="1422" />
	<plugin fragment="true" id="org.eclipse.rse.subsystems.files.local.nl_de" unpack="false" version="4.5.0.v20150804081228" download-size="1386" install-size="1386" />
	<plugin fragment="true" id="org.eclipse.rse.subsystems.files.scp.nl_de" unpack="false" version="4.5.0.v20150804081228" download-size="1384" install-size="1384" />
	<plugin fragment="true" id="org.eclipse.rse.subsystems.files.ssh.nl_de" unpack="false" version="4.5.0.v20150804081228" download-size="1384" install-size="1384" />
	<plugin fragment="true" id="org.eclipse.rse.subsystems.processes.core.nl_de" unpack="false" version="4.5.0.v20150804081228" download-size="2927" install-size="2927" />
	<plugin fragment="true" id="org.eclipse.rse.subsystems.processes.dstore.nl_de" unpack="false" version="4.5.0.v20150804081228" download-size="1403" install-size="1403" />
	<plugin fragment="true" id="org.eclipse.rse.subsystems.processes.local.nl_de" unpack="false" version="4.5.0.v20150804081228" download-size="1387" install-size="1387" />
	<plugin fragment="true" id="org.eclipse.rse.subsystems.processes.shell.linux.nl_de" unpack="false" version="4.5.0.v20150804081228" download-size="1419" install-size="1419" />
	<plugin fragment="true" id="org.eclipse.rse.subsystems.shells.core.nl_de" unpack="false" version="4.5.0.v20150804081228" download-size="1386" install-size="1386" />
	<plugin fragment="true" id="org.eclipse.rse.subsystems.shells.dstore.nl_de" unpack="false" version="4.5.0.v20150804081228" download-size="1387" install-size="1387" />
	<plugin fragment="true" id="org.eclipse.rse.subsystems.shells.local.nl_de" unpack="false" version="4.5.0.v20150804081228" download-size="1387" install-size="1387" />
	<plugin fragment="true" id="org.eclipse.rse.subsystems.shells.ssh.nl_de" unpack="false" version="4.5.0.v20150804081228" download-size="1386" install-size="1386" />
	<plugin fragment="true" id="org.eclipse.rse.subsystems.shells.telnet.nl_de" unpack="false" version="4.5.0.v20150804081228" download-size="1387" install-size="1387" />
	<plugin fragment="true" id="org.eclipse.rse.subsystems.terminals.core.nl_de" unpack="false" version="4.5.0.v20150804081228" download-size="1387" install-size="1387" />
	<plugin fragment="true" id="org.eclipse.rse.subsystems.terminals.ssh.nl_de" unpack="false" version="4.5.0.v20150804081228" download-size="1388" install-size="1388" />
	<plugin fragment="true" id="org.eclipse.rse.subsystems.wince.nl_de" unpack="false" version="4.5.0.v20150804081228" download-size="1427" install-size="1427" />
	<plugin fragment="true" id="org.eclipse.rse.telnet-feature.nl_de" unpack="false" version="4.5.0.v20150804081228" download-size="1541" install-size="1541" />
	<plugin fragment="true" id="org.eclipse.rse.terminals-feature.nl_de" unpack="false" version="4.5.0.v20150804081228" download-size="1543" install-size="1543" />
	<plugin fragment="true" id="org.eclipse.rse.terminals.ui.nl_de" unpack="false" version="4.5.0.v20150804081228" download-size="2445" install-size="2445" />
	<plugin fragment="true" id="org.eclipse.rse.tests-feature.nl_de" unpack="false" version="4.5.0.v20150804081228" download-size="1540" install-size="1540" />
	<plugin fragment="true" id="org.eclipse.rse.tests.framework.examples.nl_de" unpack="false" version="4.5.0.v20150804081228" download-size="1388" install-size="1388" />
	<plugin fragment="true" id="org.eclipse.rse.tests.framework.nl_de" unpack="false" version="4.5.0.v20150804081228" download-size="1452" install-size="1452" />
	<plugin fragment="true" id="org.eclipse.rse.ui.capabilities.nl_de" unpack="false" version="4.5.0.v20150804081228" download-size="1382" install-size="1382" />
	<plugin fragment="true" id="org.eclipse.rse.ui.nl_de" unpack="false" version="4.5.0.v20150804081228" download-size="6448" install-size="6448" />
	<plugin fragment="true" id="org.eclipse.rse.useractions-feature.nl_de" unpack="false" version="4.5.0.v20150804081228" download-size="1543" install-size="1543" />
	<plugin fragment="true" id="org.eclipse.rse.useractions.nl_de" unpack="false" version="4.5.0.v20150804081228" download-size="3777" install-size="3777" />
	<plugin fragment="true" id="org.eclipse.rse.useractions.sdk.nl_de" unpack="false" version="4.5.0.v20150804081228" download-size="1382" install-size="1382" />
	<plugin fragment="true" id="org.eclipse.rse.wince-feature.nl_de" unpack="false" version="4.5.0.v20150804081228" download-size="1541" install-size="1541" />
	<plugin fragment="true" id="org.eclipse.tm.rapi.examples.nl_de" unpack="false" version="4.5.0.v20150804081228" download-size="1379" install-size="1379" />
	<plugin fragment="true" id="org.eclipse.tm.rapi.nl_de" unpack="false" version="4.5.0.v20150804081228" download-size="1373" install-size="1373" />
</feature>